[
    {
        "id": 0,
        "name": "tree 0",
        "area": "1220",
        "position": "1111",
        "handle":"iiii"
    },
    {
        "id": 1,
        "name": "tree 1",
        "area": "1221",
        "position": "1111",
        "handle":"iiii"
    },
    {
        "id": 2,
        "name": "tree 2",
        "area": "1222",
        "position": "1111",
        "handle":"iiii"
    },
    {
        "id": 3,
        "name": "tree 3",
        "area": "1223",
        "position": "1111",
        "handle":"iiii"
    },
    {
        "id": 4,
        "name": "tree 4",
        "area": "1224",
        "position": "1111",
        "handle":"iiii"
    },
    {
        "id": 5,
        "name": "tree 5",
        "area": "1225",
        "position": "1111",
        "handle":"iiii"

    },
    {
        "id": 6,
        "name": "tree 6",
        "area": "1226",
        "position": "1111",
        "handle":"iiii"
    },
    {
        "id": 7,
        "name": "tree 7",
        "area": "1227",
        "position": "1111",
        "handle":"iiii"
    },
    {
        "id": 8,
        "name": "tree 8",
        "area": "1228",
        "position": "1111",
        "handle":"iiii"
    },
    {
        "id": 9,
        "name": "tree 9",
        "area": "1229",
        "position": "1111",
        "handle":"iiii"
    },
    {
        "id": 10,
        "name": "tree 10",
        "area": "12210",
        "position": "1111",
        "handle":"iiii"
    },
    {
        "id": 11,
        "name": "tree 11",
        "area": "12211",
        "position": "1111",
        "handle":"iiii"
    },
    {
        "id": 12,
        "name": "tree 12",
        "area": "12212",
        "position": "1111",
        "handle":"iiii"
    },
    {
        "id": 13,
        "name": "tree 13",
        "area": "12213",
        "position": "1111",
        "handle":"iiii"
    },
    {
        "id": 14,
        "name": "tree 14",
        "area": "12214",
        "position": "1111",
        "handle":"iiii"
    },
    {
        "id": 15,
        "name": "tree 15",
        "area": "12215",
        "position": "1111",
        "handle":"iiii"
    },
    {
        "id": 16,
        "name": "tree 16",
        "area": "12216",
        "position": "1111",
        "handle":"iiii"
    },
    {
        "id": 17,
        "name": "tree 17",
        "area": "12217",
        "position": "1111",
        "handle":"iiii"
    },
    {
        "id": 18,
        "name": "tree 18",
        "area": "12218",
        "position": "1111",
        "handle":"iiii"
    },
    {
        "id": 19,
        "name": "tree 19",
        "area": "12219",
        "position": "1111",
        "handle":"iiii"
    },
    {
        "id": 20,
        "name": "tree 20",
        "area": "12220",
        "position": "1111",
        "handle":"iiii"
    }
]